neurotune/__init__.py
neurotune/controllers.py
neurotune/evaluators.py
neurotune/optimizers.py
neurotune/utils.py
neurotune-0.2.6.dist-info/AUTHORS
neurotune-0.2.6.dist-info/LICENSE
neurotune-0.2.6.dist-info/METADATA
neurotune-0.2.6.dist-info/WHEEL
neurotune-0.2.6.dist-info/top_level.txt
neurotune-0.2.6.dist-info/RECORD
