Metadata-Version: 2.1
Name: neurotune
Version: 0.2.6
Summary: A Python library for optimising neuronal models
Home-page: https://github.com/NeuralEnsemble/neurotune
Author: Michael Vella, Padraig Gleeson
Author-email: mv333@cam.ac.uk, p.gleeson@gmail.com
License: BSD
Classifier: Development Status :: 3 - Alpha
Classifier: Intended Audience :: Science/Research
Classifier: License :: OSI Approved :: BSD License
Classifier: Natural Language :: English
Classifier: Operating System :: OS Independent
Classifier: Programming Language :: Python :: 3
Classifier: Programming Language :: Python :: 3.7
Classifier: Programming Language :: Python :: 3.8
Classifier: Programming Language :: Python :: 3.9
Classifier: Programming Language :: Python :: 3.10
Classifier: Programming Language :: Python :: 3.11
Classifier: Topic :: Scientific/Engineering
License-File: LICENSE
License-File: AUTHORS
Requires-Dist: scipy
Requires-Dist: inspyred
Requires-Dist: pyelectro
